brotab/__init__.py
brotab/__version__.py
brotab/api.py
brotab/const.py
brotab/env.py
brotab/files.py
brotab/inout.py
brotab/main.py
brotab/operations.py
brotab/parallel.py
brotab/platform.py
brotab/tab.py
brotab/utils.py
brotab/wait.py
brotab/albert/Brotab.qss
brotab/albert/__init__.py
brotab/albert/brotab_search.py
brotab/mediator/__init__.py
brotab/mediator/brotab_mediator.py
brotab/mediator/chromium_mediator.json
brotab/mediator/const.py
brotab/mediator/firefox_mediator.json
brotab/mediator/http_server.py
brotab/mediator/log.py
brotab/mediator/remote_api.py
brotab/mediator/runner.py
brotab/mediator/sig.py
brotab/mediator/support.py
brotab/mediator/transport.py
brotab/search/__init__.py
brotab/search/index.py
brotab/search/query.py
brotab/tests/__init__.py
brotab/tests/mocks.py
brotab/tests/test_brotab.py
brotab/tests/test_inout.py
brotab/tests/test_integration.py
brotab/tests/test_main.py
brotab/tests/test_utils.py
brotab/tests/utils.py
brotab-1.5.0.data/data/config/Brotab.qss
brotab-1.5.0.data/data/config/chromium_mediator.json
brotab-1.5.0.data/data/config/firefox_mediator.json
brotab-1.5.0.dist-info/LICENSE
brotab-1.5.0.dist-info/METADATA
brotab-1.5.0.dist-info/WHEEL
brotab-1.5.0.dist-info/entry_points.txt
brotab-1.5.0.dist-info/top_level.txt
brotab-1.5.0.dist-info/RECORD
