Metadata-Version: 2.2
Name: brotab
Version: 1.5.0
Summary: Control your browser's tabs from the command line
Home-page: https://github.com/balta2ar/brotab
Author: Yuri Bochkarev
Author-email: baltazar.bz@gmail.com
License: MIT
Classifier: License :: OSI Approved :: MIT License
Classifier: Programming Language :: Python
Classifier: Programming Language :: Python :: 3
Classifier: Programming Language :: Python :: 3.10
Classifier: Programming Language :: Python :: 3.11
Classifier: Programming Language :: Python :: 3.12
Classifier: Programming Language :: Python :: Implementation :: CPython
License-File: LICENSE
Requires-Dist: Flask==2.2.2
Requires-Dist: requests==2.24.0
Requires-Dist: psutil==5.8.0
Requires-Dist: Werkzeug<3.0
Requires-Dist: setuptools==75.8.0
Dynamic: author
Dynamic: author-email
Dynamic: classifier
Dynamic: description
Dynamic: description-content-type
Dynamic: home-page
Dynamic: license
Dynamic: requires-dist
Dynamic: summary
